a02_monitoring/__init__.py
a02_monitoring/_modidx.py
a02_monitoring/config.py
a02_monitoring/core.py
a02_monitoring/download.py
a02_monitoring/monitoring.py
a02_monitoring/mov_helper.py
a02_monitoring/nback_helper.py
a02_monitoring-0.0.1.dist-info/LICENSE
a02_monitoring-0.0.1.dist-info/METADATA
a02_monitoring-0.0.1.dist-info/WHEEL
a02_monitoring-0.0.1.dist-info/entry_points.txt
a02_monitoring-0.0.1.dist-info/top_level.txt
a02_monitoring-0.0.1.dist-info/RECORD
